setup.cfg
setup.py
cisco_ssapi/__init__.py
cisco_ssapi/eox.py
cisco_ssapi/scripts.py
cisco_ssapi.egg-info/PKG-INFO
cisco_ssapi.egg-info/SOURCES.txt
cisco_ssapi.egg-info/dependency_links.txt
cisco_ssapi.egg-info/entry_points.txt
cisco_ssapi.egg-info/not-zip-safe
cisco_ssapi.egg-info/requires.txt
cisco_ssapi.egg-info/test_info.txt
cisco_ssapi.egg-info/top_level.txt