Metadata-Version: 1.0
Name: cisco-ssapi
Version: 1.0dev
Summary: Python API and CLI access to Cisco's SSAPI
Home-page: http://github.com/cluther/cisco_ssapi
Author: Chet Luther
Author-email: chet.luther@gmail.com
License: GPLv3
Keywords: cisco ssapi eox
Platform: UNKNOWN
Classifier: Development Status :: 4 - Beta
Classifier: Environment :: Console
Classifier: Intended Audience :: Developers
Classifier: Intended Audience :: Information Technology
Classifier: License :: OSI Approved :: GNU General Public License (GPL)
Classifier: Natural Language :: English
Classifier: Operating System :: OS Independent
Classifier: Programming Language :: Python
Classifier: Programming Language :: Python :: 2.4
Classifier: Programming Language :: Python :: 2.5
Classifier: Programming Language :: Python :: 2.6
Classifier: Topic :: Software Development :: Libraries :: Python Modules
Classifier: Topic :: Utilities
